<PAMDataset>
  <Metadata domain="IMAGE_STRUCTURE">
    <MDI key="COMPRESSION">JPEG</MDI>
    <MDI key="INTERLEAVE">PIXEL</MDI>
    <MDI key="SOURCE_COLOR_SPACE">YCbCr</MDI>
  </Metadata>
  <PAMRasterBand band="1">
    <Metadata domain="IMAGE_STRUCTURE">
      <MDI key="COMPRESSION">JPEG</MDI>
    </Metadata>
    <Metadata>
      <MDI key="STATISTICS_APPROXIMATE">YES</MDI>
      <MDI key="STATISTICS_MAXIMUM">249</MDI>
      <MDI key="STATISTICS_MEAN">198.99853969166</MDI>
      <MDI key="STATISTICS_MINIMUM">6</MDI>
      <MDI key="STATISTICS_STDDEV">35.706315116067</MDI>
    </Metadata>
  </PAMRasterBand>
  <PAMRasterBand band="2">
    <Metadata domain="IMAGE_STRUCTURE">
      <MDI key="COMPRESSION">JPEG</MDI>
    </Metadata>
    <Metadata>
      <MDI key="STATISTICS_APPROXIMATE">YES</MDI>
      <MDI key="STATISTICS_MAXIMUM">246</MDI>
      <MDI key="STATISTICS_MEAN">192.71942928277</MDI>
      <MDI key="STATISTICS_MINIMUM">8</MDI>
      <MDI key="STATISTICS_STDDEV">35.337897025405</MDI>
    </Metadata>
  </PAMRasterBand>
  <PAMRasterBand band="3">
    <Metadata domain="IMAGE_STRUCTURE">
      <MDI key="COMPRESSION">JPEG</MDI>
    </Metadata>
    <Metadata>
      <MDI key="STATISTICS_APPROXIMATE">YES</MDI>
      <MDI key="STATISTICS_MAXIMUM">244</MDI>
      <MDI key="STATISTICS_MEAN">175.55666475151</MDI>
      <MDI key="STATISTICS_MINIMUM">4</MDI>
      <MDI key="STATISTICS_STDDEV">38.344227436614</MDI>
    </Metadata>
  </PAMRasterBand>
</PAMDataset>
